geunduun/__init__.py
geunduun/docker_wrapper/runpod/Dockerfile
geunduun/docker_wrapper/runpod/wrapper_script.sh
geunduun/enums.py
geunduun/managers/base.py
geunduun/managers/runpod.py
geunduun-0.1.0.dist-info/WHEEL
geunduun-0.1.0.dist-info/entry_points.txt
geunduun-0.1.0.dist-info/METADATA
geunduun-0.1.0.dist-info/RECORD
