Metadata-Version: 2.3
Name: geunduun
Version: 0.1.0
Summary: Add your description here
Author: richardSHkim
Author-email: richardSHkim <kshtrue95@gmail.com>
Requires-Dist: httpx>=0.28.1
Requires-Dist: python-dotenv>=1.1.1
Requires-Dist: pyyaml>=6.0.3
Requires-Python: >=3.11
